<?xml version='1.0' encoding='UTF-8'?>
<tv><channel id="La 2"><display-name>La 2</display-name></channel><programme channel="La 2" start="20241204111000 +0100" stop="20241204115500 +0100"><title>Documenta2 Dioses De Egipto</title><desc>Damos la bienvenida al nacimiento de Horus, prototipo del superhéroe por excelencia. El dios con cabeza de halcón, criado y protegido por su madre.</desc><category lang="en">Categoria</category></programme><programme channel="La 2" start="20241204115500 +0100" stop="20241204122000 +0100"><title>80 Cm</title><desc>"80 cm" es el programa de senderismo de La 2 que esta temporadas caminará por la geografía española de la mano del actor Juan José Ballesta.</desc><category lang="en">Categoria</category></programme><programme channel="La 2" start="20241204122000 +0100" stop="20241204124800 +0100"><title>Documental  Diario De Un Nomada, Expedicion Trajano</title><desc>Miquel Silvestre amanece en el maravilloso paraje natural de los Abruzzos, en pleno corazón de Italia, a orillas del lago Campotosto.</desc><category lang="en">Categoria</category></programme><programme channel="La 2" start="20241204124800 +0100" stop="20241204132000 +0100"><title>Documental  Diario De Un Nomada, Expedicion Trajano</title><desc>Miquel Silvestre atraviesa la península italiana para llegar a la costa del mar Adriático rumbo a Split, en Croacia.</desc><category lang="en">Categoria</category></programme><programme channel="La 2" start="20241204132000 +0100" stop="20241204145500 +0100"><title>Mañanas De Cine Tres Forajidos Y Un Pistolero</title><desc>Tres muchachos, deseosos de vivir aventuras y de escapar de una vida de miseria y malos tratos, se unen a un viejo y legendario atracador de bancos.</desc><category lang="en">Categoria</category></programme><programme channel="La 2" start="20241204145500 +0100" stop="20241204154500 +0100"><title>Un Pais Para Comerselo</title><desc>La aventura de Imanol y Juan comienza atravesando un bosque por el que están felizmente perdidos.</desc><category lang="en">Categoria</category></programme><programme channel="La 2" start="20241204154500 +0100" stop="20241204163000 +0100"><title>Saber Y Ganar</title><desc>Programa concurso diario en el que tres participantes demuestran sus conocimientos y su agilidad mental.</desc><category lang="en">Categoria</category></programme><programme channel="La 2" start="20241204163000 +0100" stop="20241204172000 +0100"><title>Grandes Documentales La Cebra Afortunada</title><desc>En la naturaleza, están los herbívoros a quienes nada sonríe de inmediato (apenas nacidos ya comidos) y otros a quienes les va mejor.</desc><category lang="en">Categoria</category></programme><programme channel="La 2" start="20241204172000 +0100" stop="20241204181000 +0100"><title>Grandes Documentales Fauna Iberica</title><desc>Esta serie pretende mostrar aspectos desconocidos de la fauna ibérica: las relaciones ecológicas, el comportamiento, los problemas y la conservación</desc><category lang="en">Categoria</category></programme></tv>